Metadata-Version: 1.0
Name: alice-demo2
Version: 1.0
Summary: Alice open source package
Home-page: UNKNOWN
Author: Alice
Author-email: srossross@gmail.com
License: BSD
Platform: UNKNOWN
